pipecat_ai_small_webrtc_prebuilt/__init__.py
pipecat_ai_small_webrtc_prebuilt/frontend.py
pipecat_ai_small_webrtc_prebuilt/client/dist/favicon.svg
pipecat_ai_small_webrtc_prebuilt/client/dist/index.html
pipecat_ai_small_webrtc_prebuilt/client/dist/pipecat-logo.svg
pipecat_ai_small_webrtc_prebuilt/client/dist/assets/geist-cyrillic-wght-normal-CHSlOQsW.woff2
pipecat_ai_small_webrtc_prebuilt/client/dist/assets/geist-latin-ext-wght-normal-DMtmJ5ZE.woff2
pipecat_ai_small_webrtc_prebuilt/client/dist/assets/geist-latin-wght-normal-Dm3htQBi.woff2
pipecat_ai_small_webrtc_prebuilt/client/dist/assets/geist-mono-cyrillic-wght-normal-BZdD_g9V.woff2
pipecat_ai_small_webrtc_prebuilt/client/dist/assets/geist-mono-latin-ext-wght-normal-b6lpi8_2.woff2
pipecat_ai_small_webrtc_prebuilt/client/dist/assets/geist-mono-latin-wght-normal-Cjtb1TV-.woff2
pipecat_ai_small_webrtc_prebuilt/client/dist/assets/index-CLuiFqWA.css
pipecat_ai_small_webrtc_prebuilt/client/dist/assets/index-DLrHYund.js
pipecat_ai_small_webrtc_prebuilt/client/dist/assets/index.module-Cv1O8B4r.js
pipecat_ai_small_webrtc_prebuilt/client/dist/assets/index.module-i9LT_tp7.js
pipecat_ai_small_webrtc_prebuilt-2.0.4.dist-info/METADATA
pipecat_ai_small_webrtc_prebuilt-2.0.4.dist-info/WHEEL
pipecat_ai_small_webrtc_prebuilt-2.0.4.dist-info/top_level.txt
pipecat_ai_small_webrtc_prebuilt-2.0.4.dist-info/RECORD
