Metadata-Version: 2.4
Name: pipecat-ai-small-webrtc-prebuilt
Version: 2.0.4
Summary: A simple, ready-to-use client for testing the SmallWebRTCTransport.
License: BSD 2-Clause License
Project-URL: homepage, https://github.com/pipecat-ai/small-webrtc-prebuilt
Project-URL: source, https://github.com/pipecat-ai/small-webrtc-prebuilt
Project-URL: issues, https://github.com/pipecat-ai/small-webrtc-prebuilt/issues
Keywords: webrtc,pipecat,voice,ai
Classifier: Development Status :: 5 - Production/Stable
Classifier: Intended Audience :: Developers
Classifier: Topic :: Communications :: Conferencing
Classifier: Topic :: Multimedia :: Sound/Audio
Classifier: Topic :: Multimedia :: Video
Requires-Python: >=3.10
Requires-Dist: fastapi[all]
